{"slug":"dansville","taxonomy":"locations","route":"/locations/dansville","title":"Commercial Roofing in Dansville, MI | Commercial Roofing Contractors of Lansing","metaDescription":"Commercial roof repair for Dansville, MI's grain and ag-service buildings, small retail, and community buildings in Vevay Township, Ingham County.","internalLinks":[{"anchor":"Eaton Rapids Still Roofs Like the Island City It Was Built To Be","slug":"eaton-rapids","taxonomy":"locations","href":"/locations/eaton-rapids"},{"anchor":"Fowlerville's Industrial Park Roofs Answer to the Fairgrounds Calendar","slug":"fowlerville","taxonomy":"locations","href":"/locations/fowlerville"},{"anchor":"Grand Ledge Splits Between Riverside Manufacturing and a Historic Main Street","slug":"grand-ledge","taxonomy":"locations","href":"/locations/grand-ledge"},{"anchor":"Lake Lansing Humidity and School Campus Roofs Around Haslett","slug":"haslett","taxonomy":"locations","href":"/locations/haslett"},{"anchor":"Holt's Roofs Are Smaller and the Repair-vs-Replace Math Is Tighter","slug":"holt","taxonomy":"locations","href":"/locations/holt"},{"anchor":"Keeping Drains and Scuppers Working Through a Lansing Winter","slug":"roof-drains-scuppers","taxonomy":"services","href":"/services/roof-drains-scuppers"},{"anchor":"Roofs Over Practices That Can't Reschedule a Full Waiting Room","slug":"medical-office-building-roofing","taxonomy":"project-types","href":"/project-types/medical-office-building-roofing"},{"anchor":"Roof Documentation That Holds Up Through the Claims Process","slug":"insurance-restoration","taxonomy":"industries","href":"/industries/insurance-restoration"}],"html":"<h1>Honest Roofing Help for a Village the Size of Dansville</h1>\n<p>Dansville is an unincorporated village in Ingham County's Vevay Township, small enough that it doesn't have its own municipal government, let alone a commercial district. What roofing work exists here is a handful of buildings &mdash; a grain or ag-service operation, a small retail building or two, maybe a church &mdash; and we want to be upfront that this is about as small-scale as commercial roofing gets in our service area.</p>\n<h2>What Actually Needs a Commercial Roof in Dansville</h2>\n<p>There's no pretending Dansville has a business district. The buildings that need commercial-grade roofing here are a small number: an ag-service or grain-handling building, a small retail operation or gas station, and community buildings like a church or a hall that host local activity. Everything else is residential.</p>\n<p>We're honest about that with every owner who calls, because we'd rather set accurate expectations than describe Dansville as something it isn't. A roofing contractor that only wants big jobs isn't going to show up for a town like this, and that's exactly the gap we're built to fill.</p>\n<p>We also get calls occasionally from owners just outside Dansville proper, on the county roads that feed into it, asking whether we cover their building too. The answer is almost always yes &mdash; the same route that brings us to Dansville usually passes within a few minutes of those outlying properties.</p>\n<h2>Why Small Ag-Service Buildings Need Real Attention</h2>\n<p>The grain and ag-service buildings around Dansville often run older metal roofs that have been in place for decades with minimal maintenance, because the roof isn't top of mind during a farming operation's busy season. By the time we get a call, we're frequently looking at a roof that's been leaking intermittently for a while.</p>\n<p>These buildings also store product or equipment whose value can exceed the roof's replacement cost many times over, which is the argument we make for catching problems early rather than waiting for a full-blown leak during harvest.</p>\n<p>When we do finally get out to one of these buildings, we spend as much time in the interior as we do on the roof itself, checking for the secondary damage a long-term leak usually leaves behind. Catching that early, before it spreads into structural framing, keeps the total repair cost from ballooning past what the roof work alone would have cost.</p>\n<h2>A Church or Community Building Roof Is a Different Kind of Decision</h2>\n<p>When the building in question is a church or a community hall, the roofing decision usually runs through a small board or committee working with a limited, donation-based budget. We adjust how we present options accordingly &mdash; clear, itemized, and phased where possible, rather than a single large number that a volunteer board can't act on.</p>\n<p>We've found that breaking a roof project into phases &mdash; address active leaks and flashing first, defer larger membrane work to the following budget cycle &mdash; lets these buildings get the most urgent problems solved without waiting for a capital campaign to fund everything at once.</p>\n<ul>\n<li>Active leak points and how long water intrusion has likely been occurring</li>\n<li>Flashing condition at any roof penetrations or wall transitions</li>\n<li>Fastener and seam integrity on metal roof sections</li>\n<li>Deck and insulation condition where water has already gotten in</li>\n<li>Gutter and drainage function relative to the roof's size and pitch</li>\n<li>Remaining service life of the existing roof system</li>\n<li>Whether a phased repair approach makes sense given the owner's budget</li>\n</ul>\n<h2>What We Won't Do in a Town This Size</h2>\n<p>We won't recommend a full system replacement on a Dansville building when a targeted repair genuinely solves the problem, and we won't inflate a small job to make a drive-out visit worth our time. If a fifteen-hundred-square-foot building needs a flashing fix, that's what we quote.</p>\n<p>We also won't promise a same-day crew for routine work. Dansville is a drive-out stop on our route, not a base, and being straight about that upfront avoids wasting an owner's time with unrealistic expectations.</p>\n<h2>Getting Started on a Building This Small</h2>\n<p>The process is the same as anywhere else we work: an <a href=\"/services/commercial-roof-inspection\">inspection</a>, photo documentation, and a plain-language explanation of what we found and what it means. The difference in a town like Dansville is mostly in how we frame the budget conversation, since owners here are often working with tighter margins or a volunteer board rather than a corporate facilities budget.</p>\n<p>If your building only needs a small fix, we'll say so and price it accordingly. That's true whether the roof is over a grain bin or a sanctuary.</p>\n<h2>Dansville Roofing Questions</h2>\n<h3>Is our building really too small for a real commercial roofer to take seriously?</h3>\n<p>No. We inspect and quote buildings this size the same way we would a larger one, thoroughly, with documentation, and without inflating the scope.</p>\n<h3>Our church roof has a slow leak and a small budget. What are our options?</h3>\n<p>We can often phase the work: fix active leaks and flashing issues first, defer larger membrane replacement to a later budget cycle, so the most urgent problem gets solved without waiting to fund everything at once.</p>\n<h3>How do you handle scheduling for a town without a lot of commercial buildings?</h3>\n<p>We treat Dansville as a stop along a broader Ingham County route rather than a standalone trip, which keeps costs reasonable, though we're upfront that it's not a same-day service area for routine work.</p>\n<h3>What's the biggest risk to an old grain or ag-service building roof out here?</h3>\n<p>Long gaps between any roof attention at all. These roofs often go years unmonitored, so small fastener or flashing issues turn into real leaks by the time anyone notices.</p>\n<h3>Will you tell us if our building just needs a repair instead of a full roof?</h3>\n<p>Yes. If a targeted repair solves the actual problem, that's what we recommend and quote, regardless of building size or type.</p>","image":"/images/locations/commercial-roofing-contractors-dansville-mi.webp"}