{
 "slug": "potterville",
 "taxonomy": "locations",
 "route": "/locations/potterville",
 "title": "Commercial Roofing in Potterville, MI | Commercial Roofing Contractors of Lansing",
 "metaDescription": "Commercial roofing for Potterville, MI: small industrial buildings near I-69, Main Street storefronts, and village offices. Inspection, repair, replacement.",
 "internalLinks": [
  {
   "anchor": "Holt's Roofs Are Smaller and the Repair-vs-Replace Math Is Tighter",
   "slug": "holt",
   "taxonomy": "locations",
   "href": "/locations/holt"
  },
  {
   "anchor": "What Laingsburg's Small Retail and Ag-Service Building Owners Should Expect From a Roof Inspection",
   "slug": "laingsburg",
   "taxonomy": "locations",
   "href": "/locations/laingsburg"
  },
  {
   "anchor": "Eastwood Towne Center's Roofs Are One Property With a Dozen Different Tenants",
   "slug": "lansing-township",
   "taxonomy": "locations",
   "href": "/locations/lansing-township"
  },
  {
   "anchor": "Roofing for Leslie's Small Manufacturers and Downtown Storefronts",
   "slug": "leslie",
   "taxonomy": "locations",
   "href": "/locations/leslie"
  },
  {
   "anchor": "Mason Roofs Range From the Ingham County Courthouse to Dart Container's Production Floors",
   "slug": "mason",
   "taxonomy": "locations",
   "href": "/locations/mason"
  },
  {
   "anchor": "What a Roof Recover Can Hide — and When It Shouldn't",
   "slug": "roof-recover-overlay",
   "taxonomy": "services",
   "href": "/services/roof-recover-overlay"
  },
  {
   "anchor": "Roofs Over Practices That Can't Reschedule a Full Waiting Room",
   "slug": "medical-office-building-roofing",
   "taxonomy": "project-types",
   "href": "/project-types/medical-office-building-roofing"
  },
  {
   "anchor": "Keeping Stores Open While the Roof Above Them Gets Fixed",
   "slug": "retail-chain-operators",
   "taxonomy": "industries",
   "href": "/industries/retail-chain-operators"
  }
 ],
 "html": "<h1>Roofing Decisions for Potterville's Small Commercial Buildings</h1>\n<p>Potterville is a village of about twenty-six hundred people off I-69 in Eaton County, roughly twenty minutes southwest of our Lansing office. There's no commercial district to speak of &mdash; a short block of Main Street storefronts, a school, a few small industrial buildings near the interchange, and the village offices that keep the place running. We treat every one of those roofs like it matters, because to whoever owns it, it does.</p>\n<h2>What's Actually on Potterville's Roofs</h2>\n<p>Drive the loop from the I-69 interchange into the village and you'll see the whole commercial roof inventory in about five minutes. A couple of small manufacturing or machine-shop buildings sit near the highway, built with low-slope metal or single-ply membrane roofs designed for function, not appearance. Closer to the village center there are a handful of flat-roofed storefronts, a bank branch, a gas station, and the buildings that house Potterville's schools and village government.</p>\n<p>None of this is warehouse-scale work. A roof here might cover three thousand square feet or twelve thousand, rarely more. That changes the math on material selection and how we schedule the crew, but it doesn't change the seriousness of the decision for the person who owns the building.</p>\n<h2>Eaton County Freeze-Thaw Is Harder on Small Roofs Than Owners Expect</h2>\n<p>Mid-Michigan winters put every flat and low-slope roof through repeated freeze-thaw cycles, and small commercial buildings often show the damage first because they were built with thinner budgets and fewer redundancies than a large regional facility. Water gets into a seam, freezes, expands, and by March the membrane has lifted somewhere it wasn't lifted in November.</p>\n<p>On an older built-up or modified bitumen roof &mdash; common on Potterville's Main Street block &mdash; that cycle chews at flashing details and parapet caps first. On a newer metal building near the interchange, the failure point is usually at panel laps and penetrations rather than the field of the roof itself.</p>\n<h2>What a Bad Call Costs an Owner Here</h2>\n<p>We tell every Potterville property owner the same thing we'd tell a client with a hundred-thousand-square-foot warehouse: the wrong roofing decision doesn't get cheaper because the building is small. A coating applied over a membrane that's already failing at the seams buys a season, not a decade. A patch job on a roof that needs a full recover just delays a bigger bill and adds interior damage to the tab.</p>\n<p>Because these buildings often carry tighter budgets and less reserve, a bad decision here can hurt worse, proportionally, than the same mistake on a larger commercial property. That's the lens we use walking a Potterville roof &mdash; not what's cheapest today, but what actually holds up through the next several winters.</p>\n<ul>\n<li>Water stains on ceiling tiles near exterior walls or parapets</li>\n<li>Visible membrane lifting or wrinkling at seams</li>\n<li>Ponding water that doesn't drain within 48 hours after rain</li>\n<li>Rusted or loose flashing around rooftop units and vents</li>\n<li>Interior doors or windows that have started sticking, a sign of structural moisture</li>\n<li>Granule loss or bare spots on modified bitumen roofing</li>\n<li>Ice buildup at the roof edge every winter in the same spot</li>\n</ul>\n<h2>How We Handle a Village-Scale Job</h2>\n<p>We don't keep a standing crew in Potterville, and we're honest about that upfront &mdash; this is a drive-out market for us, not a home base. Practically, that means we group visits, plan routes along the I-69/I-96 corridor, and give straight timelines rather than pretending we can be on-site same-day for routine work. Our <a href=\"/services/commercial-roof-inspection\">roof inspection process</a> stays the same regardless of the drive.</p>\n<p>For emergency leaks, we prioritize based on what's actually failing &mdash; active water intrusion during a storm moves ahead of a scheduled inspection, no matter which town it's in. For everything else, we walk the roof, document the condition with photos, and put a number in front of the owner before any work starts.</p>\n<h2>Getting a Straight Answer Before You Spend Money</h2>\n<p>A lot of small-building owners in towns like Potterville have been quoted work by contractors who never actually walked the roof, or who padded a bid because they assumed a small job wasn't worth doing carefully. We inspect first, document what we find, and explain the tradeoffs between a coating, a recover, and a full tear-off in plain terms.</p>\n<p>If your building only needs a repair, we say so. If it needs more, we explain why, in language you can bring to a board meeting or a lender, not marketing language that falls apart under questions.</p>\n<h2>Questions From Potterville Building Owners</h2>\n<h3>Is my building too small for a commercial roofing contractor to bother with?</h3>\n<p>No. We work on Main Street storefronts and small shop buildings around Potterville regularly. A three-thousand-square-foot roof gets the same inspection rigor as a much bigger one.</p>\n<h3>Should I get a metal roof or a membrane roof on a small industrial building near the interchange?</h3>\n<p>It depends on the existing structure and how the building is used. Metal panel systems handle the freeze-thaw cycle well and hold up to wind, but a single-ply membrane can be the better call on a lower-slope structure with existing penetrations. We'll walk you through both during the inspection rather than pushing one system by default.</p>\n<h3>How fast can you get to Potterville after a storm?</h3>\n<p>Active leaks get prioritized regardless of location. For routine inspections and scheduled work, we build Potterville into a broader Eaton County route rather than a same-day dispatch, and we give you a real date instead of a vague promise.</p>\n<h3>Do you handle insurance documentation for storm damage on a small commercial roof?</h3>\n<p>Yes. We document roof condition with photos and a written assessment an owner can hand to an adjuster. We don't promise a claim outcome &mdash; that's between you and your carrier &mdash; but we make sure the documentation actually supports your position.</p>\n<h3>Can you just coat my roof instead of replacing it?</h3>\n<p>Sometimes, if the substrate underneath is sound. A <a href=\"/services/silicone-roof-coatings\">silicone or acrylic coating</a> extends the life of a roof that's aging but not yet failing at the seams. If the membrane underneath is already compromised, we'll tell you a coating is a temporary fix, not a solution, before you spend the money.</p>",
 "image": "/images/locations/commercial-roofing-contractors-potterville-mi.webp"
}
